types_checker/__init__.py
types_checker/types_checker.py
types_checker-1.0.0.dist-info/LICENSE
types_checker-1.0.0.dist-info/METADATA
types_checker-1.0.0.dist-info/WHEEL
types_checker-1.0.0.dist-info/top_level.txt
types_checker-1.0.0.dist-info/RECORD
